python_swiftclient-4.9.0.data/data/share/man/man1/swift.1
swiftclient/__init__.py
swiftclient/authv1.py
swiftclient/client.py
swiftclient/command_helpers.py
swiftclient/exceptions.py
swiftclient/multithreading.py
swiftclient/requests_compat.py
swiftclient/service.py
swiftclient/shell.py
swiftclient/utils.py
swiftclient/version.py
python_swiftclient-4.9.0.dist-info/AUTHORS
python_swiftclient-4.9.0.dist-info/LICENSE
python_swiftclient-4.9.0.dist-info/METADATA
python_swiftclient-4.9.0.dist-info/WHEEL
python_swiftclient-4.9.0.dist-info/entry_points.txt
python_swiftclient-4.9.0.dist-info/pbr.json
python_swiftclient-4.9.0.dist-info/top_level.txt
python_swiftclient-4.9.0.dist-info/RECORD
