Metadata-Version: 2.1
Name: python-swiftclient
Version: 4.9.0
Summary: OpenStack Object Storage API Client Library
Home-page: https://docs.openstack.org/python-swiftclient/latest/
Author: OpenStack
Author-email: openstack-discuss@lists.openstack.org
License: Apache License, Version 2.0
Project-URL: Bug Tracker, https://bugs.launchpad.net/python-swiftclient
Project-URL: Documentation, https://docs.openstack.org/python-swiftclient/latest/
Project-URL: Release Notes, https://opendev.org/openstack/python-swiftclient/src/branch/master/ChangeLog
Project-URL: Source Code, https://opendev.org/openstack/python-swiftclient
Classifier: Environment :: OpenStack
Classifier: Intended Audience :: Information Technology
Classifier: Intended Audience :: System Administrators
Classifier: License :: OSI Approved :: Apache Software License
Classifier: Operating System :: POSIX :: Linux
Classifier: Operating System :: Microsoft :: Windows
Classifier: Programming Language :: Python
Classifier: Programming Language :: Python :: 3
Classifier: Programming Language :: Python :: 3.7
Classifier: Programming Language :: Python :: 3.8
Classifier: Programming Language :: Python :: 3.9
Classifier: Programming Language :: Python :: 3.10
Classifier: Programming Language :: Python :: 3.11
Classifier: Programming Language :: Python :: 3.12
Classifier: Programming Language :: Python :: 3.13
Classifier: Programming Language :: Python :: 3 :: Only
Requires-Python: >=3.7
License-File: LICENSE
License-File: AUTHORS
Requires-Dist: requests>=2.4.0
Provides-Extra: keystone
Requires-Dist: python-keystoneclient>=0.7.0; extra == "keystone"
Provides-Extra: test
Requires-Dist: hacking<6.2.0,>=3.2.0; extra == "test"
Requires-Dist: coverage!=4.4,>=4.0; extra == "test"
Requires-Dist: python-keystoneclient>=0.7.0; extra == "test"
Requires-Dist: keystoneauth1>=3.4.0; extra == "test"
Requires-Dist: stestr!=3.0.0,>=2.0.0; extra == "test"
Requires-Dist: openstacksdk>=0.11.0; extra == "test"
